{
  "sample_id": "neg_00514",
  "nodes": [
    {
      "node_id": 0,
      "node_type": "function",
      "name": "initialize",
      "file": "autonomous-agent-contracts_contracts_testing_AgentBalancesUpgradeTest.sol",
      "start_line": 48,
      "end_line": 55,
      "visibility": "public",
      "is_external": false,
      "is_payable": false
    },
    {
      "node_id": 1,
      "node_type": "function",
      "name": "setAdmin",
      "file": "autonomous-agent-contracts_contracts_testing_AgentBalancesUpgradeTest.sol",
      "start_line": 57,
      "end_line": 60,
      "visibility": "public",
      "is_external": false,
      "is_payable": false
    },
    {
      "node_id": 2,
      "node_type": "function",
      "name": "setDeployer",
      "file": "autonomous-agent-contracts_contracts_testing_AgentBalancesUpgradeTest.sol",
      "start_line": 62,
      "end_line": 65,
      "visibility": "public",
      "is_external": false,
      "is_payable": false
    },
    {
      "node_id": 3,
      "node_type": "function",
      "name": "setAgentWallet",
      "file": "autonomous-agent-contracts_contracts_testing_AgentBalancesUpgradeTest.sol",
      "start_line": 68,
      "end_line": 75,
      "visibility": "public",
      "is_external": false,
      "is_payable": false
    },
    {
      "node_id": 4,
      "node_type": "function",
      "name": "withdraw",
      "file": "autonomous-agent-contracts_contracts_testing_AgentBalancesUpgradeTest.sol",
      "start_line": 77,
      "end_line": 85,
      "visibility": "public",
      "is_external": false,
      "is_payable": false
    },
    {
      "node_id": 5,
      "node_type": "function",
      "name": "withdrawETH",
      "file": "autonomous-agent-contracts_contracts_testing_AgentBalancesUpgradeTest.sol",
      "start_line": 87,
      "end_line": 95,
      "visibility": "public",
      "is_external": false,
      "is_payable": true
    },
    {
      "node_id": 6,
      "node_type": "function",
      "name": "deposit",
      "file": "autonomous-agent-contracts_contracts_testing_AgentBalancesUpgradeTest.sol",
      "start_line": 97,
      "end_line": 110,
      "visibility": "public",
      "is_external": false,
      "is_payable": false
    },
    {
      "node_id": 7,
      "node_type": "function",
      "name": "depositETH",
      "file": "autonomous-agent-contracts_contracts_testing_AgentBalancesUpgradeTest.sol",
      "start_line": 112,
      "end_line": 123,
      "visibility": "public",
      "is_external": false,
      "is_payable": true
    },
    {
      "node_id": 8,
      "node_type": "function",
      "name": "claimForAgent",
      "file": "autonomous-agent-contracts_contracts_testing_AgentBalancesUpgradeTest.sol",
      "start_line": 125,
      "end_line": 131,
      "visibility": "public",
      "is_external": false,
      "is_payable": false
    },
    {
      "node_id": 9,
      "node_type": "function",
      "name": "claimETHForAgent",
      "file": "autonomous-agent-contracts_contracts_testing_AgentBalancesUpgradeTest.sol",
      "start_line": 133,
      "end_line": 139,
      "visibility": "public",
      "is_external": false,
      "is_payable": true
    },
    {
      "node_id": 10,
      "node_type": "function",
      "name": "getLPBalance",
      "file": "autonomous-agent-contracts_contracts_testing_AgentBalancesUpgradeTest.sol",
      "start_line": 141,
      "end_line": 145,
      "visibility": "public",
      "is_external": false,
      "is_payable": false
    },
    {
      "node_id": 11,
      "node_type": "function",
      "name": "getAgentBalance",
      "file": "autonomous-agent-contracts_contracts_testing_AgentBalancesUpgradeTest.sol",
      "start_line": 147,
      "end_line": 149,
      "visibility": "public",
      "is_external": false,
      "is_payable": false
    },
    {
      "node_id": 12,
      "node_type": "function",
      "name": "_authorizeUpgrade",
      "file": "autonomous-agent-contracts_contracts_testing_AgentBalancesUpgradeTest.sol",
      "start_line": 151,
      "end_line": 154,
      "visibility": "internal",
      "is_external": false,
      "is_payable": false
    },
    {
      "node_id": 13,
      "node_type": "function",
      "name": "initialize",
      "file": "autonomous-agent-contracts_contracts_testing_AutonomousAgentDeployerUpgradeTest.sol",
      "start_line": 113,
      "end_line": 147,
      "visibility": "public",
      "is_external": false,
      "is_payable": true
    },
    {
      "node_id": 14,
      "node_type": "function",
      "name": "deployAgent",
      "file": "autonomous-agent-contracts_contracts_testing_AutonomousAgentDeployerUpgradeTest.sol",
      "start_line": 149,
      "end_line": 173,
      "visibility": "public",
      "is_external": false,
      "is_payable": true
    },
    {
      "node_id": 15,
      "node_type": "function",
      "name": "deployAgentWithETH",
      "file": "autonomous-agent-contracts_contracts_testing_AutonomousAgentDeployerUpgradeTest.sol",
      "start_line": 175,
      "end_line": 206,
      "visibility": "public",
      "is_external": false,
      "is_payable": true
    },
    {
      "node_id": 16,
      "node_type": "function",
      "name": "initializeAgent",
      "file": "autonomous-agent-contracts_contracts_testing_AutonomousAgentDeployerUpgradeTest.sol",
      "start_line": 208,
      "end_line": 256,
      "visibility": "internal",
      "is_external": false,
      "is_payable": false
    },
    {
      "node_id": 17,
      "node_type": "function",
      "name": "swapETHForSPEC",
      "file": "autonomous-agent-contracts_contracts_testing_AutonomousAgentDeployerUpgradeTest.sol",
      "start_line": 258,
      "end_line": 277,
      "visibility": "internal",
      "is_external": false,
      "is_payable": false
    },
    {
      "node_id": 18,
      "node_type": "function",
      "name": "getTokensReceived",
      "file": "autonomous-agent-contracts_contracts_testing_AutonomousAgentDeployerUpgradeTest.sol",
      "start_line": 279,
      "end_line": 286,
      "visibility": "public",
      "is_external": false,
      "is_payable": false
    },
    {
      "node_id": 19,
      "node_type": "function",
      "name": "getSPECReceived",
      "file": "autonomous-agent-contracts_contracts_testing_AutonomousAgentDeployerUpgradeTest.sol",
      "start_line": 288,
      "end_line": 295,
      "visibility": "public",
      "is_external": false,
      "is_payable": false
    },
    {
      "node_id": 20,
      "node_type": "function",
      "name": "_getTokensFromUniswap",
      "file": "autonomous-agent-contracts_contracts_testing_AutonomousAgentDeployerUpgradeTest.sol",
      "start_line": 297,
      "end_line": 304,
      "visibility": "internal",
      "is_external": false,
      "is_payable": false
    },
    {
      "node_id": 21,
      "node_type": "function",
      "name": "_getTokensFromBondingCurve",
      "file": "autonomous-agent-contracts_contracts_testing_AutonomousAgentDeployerUpgradeTest.sol",
      "start_line": 306,
      "end_line": 325,
      "visibility": "internal",
      "is_external": false,
      "is_payable": false
    },
    {
      "node_id": 22,
      "node_type": "function",
      "name": "getSPECAmountForTokens",
      "file": "autonomous-agent-contracts_contracts_testing_AutonomousAgentDeployerUpgradeTest.sol",
      "start_line": 328,
      "end_line": 331,
      "visibility": "public",
      "is_external": false,
      "is_payable": false
    },
    {
      "node_id": 23,
      "node_type": "function",
      "name": "swapExactSPECForTokens",
      "file": "autonomous-agent-contracts_contracts_testing_AutonomousAgentDeployerUpgradeTest.sol",
      "start_line": 333,
      "end_line": 377,
      "visibility": "public",
      "is_external": false,
      "is_payable": false
    },
    {
      "node_id": 24,
      "node_type": "function",
      "name": "swapExactTokensForSPEC",
      "file": "autonomous-agent-contracts_contracts_testing_AutonomousAgentDeployerUpgradeTest.sol",
      "start_line": 379,
      "end_line": 421,
      "visibility": "public",
      "is_external": false,
      "is_payable": false
    },
    {
      "node_id": 25,
      "node_type": "function",
      "name": "accumulateSwapFees",
      "file": "autonomous-agent-contracts_contracts_testing_AutonomousAgentDeployerUpgradeTest.sol",
      "start_line": 423,
      "end_line": 426,
      "visibility": "external",
      "is_external": true,
      "is_payable": false
    },
    {
      "node_id": 26,
      "node_type": "function",
      "name": "_distributeSwapFees",
      "file": "autonomous-agent-contracts_contracts_testing_AutonomousAgentDeployerUpgradeTest.sol",
      "start_line": 428,
      "end_line": 434,
      "visibility": "internal",
      "is_external": false,
      "is_payable": false
    },
    {
      "node_id": 27,
      "node_type": "function",
      "name": "deployUniswapPool",
      "file": "autonomous-agent-contracts_contracts_testing_AutonomousAgentDeployerUpgradeTest.sol",
      "start_line": 436,
      "end_line": 446,
      "visibility": "internal",
      "is_external": false,
      "is_payable": false
    },
    {
      "node_id": 28,
      "node_type": "function",
      "name": "withdrawTokens",
      "file": "autonomous-agent-contracts_contracts_testing_AutonomousAgentDeployerUpgradeTest.sol",
      "start_line": 448,
      "end_line": 451,
      "visibility": "public",
      "is_external": false,
      "is_payable": false
    },
    {
      "node_id": 29,
      "node_type": "function",
      "name": "withdrawEther",
      "file": "autonomous-agent-contracts_contracts_testing_AutonomousAgentDeployerUpgradeTest.sol",
      "start_line": 453,
      "end_line": 457,
      "visibility": "public",
      "is_external": false,
      "is_payable": true
    },
    {
      "node_id": 30,
      "node_type": "function",
      "name": "setParameter",
      "file": "autonomous-agent-contracts_contracts_testing_AutonomousAgentDeployerUpgradeTest.sol",
      "start_line": 459,
      "end_line": 462,
      "visibility": "external",
      "is_external": true,
      "is_payable": false
    },
    {
      "node_id": 31,
      "node_type": "function",
      "name": "addAlreadyExistingUniswapPool",
      "file": "autonomous-agent-contracts_contracts_testing_AutonomousAgentDeployerUpgradeTest.sol",
      "start_line": 466,
      "end_line": 471,
      "visibility": "external",
      "is_external": true,
      "is_payable": false
    },
    {
      "node_id": 32,
      "node_type": "function",
      "name": "setFeeWallet",
      "file": "autonomous-agent-contracts_contracts_testing_AutonomousAgentDeployerUpgradeTest.sol",
      "start_line": 473,
      "end_line": 476,
      "visibility": "external",
      "is_external": true,
      "is_payable": true
    },
    {
      "node_id": 33,
      "node_type": "function",
      "name": "setAdmin",
      "file": "autonomous-agent-contracts_contracts_testing_AutonomousAgentDeployerUpgradeTest.sol",
      "start_line": 478,
      "end_line": 481,
      "visibility": "external",
      "is_external": true,
      "is_payable": false
    },
    {
      "node_id": 34,
      "node_type": "function",
      "name": "changePoolCreationValue",
      "file": "autonomous-agent-contracts_contracts_testing_AutonomousAgentDeployerUpgradeTest.sol",
      "start_line": 483,
      "end_line": 485,
      "visibility": "external",
      "is_external": true,
      "is_payable": false
    },
    {
      "node_id": 35,
      "node_type": "function",
      "name": "upgradeAllAgents",
      "file": "autonomous-agent-contracts_contracts_testing_AutonomousAgentDeployerUpgradeTest.sol",
      "start_line": 487,
      "end_line": 492,
      "visibility": "external",
      "is_external": true,
      "is_payable": false
    },
    {
      "node_id": 36,
      "node_type": "function",
      "name": "_authorizeUpgrade",
      "file": "autonomous-agent-contracts_contracts_testing_AutonomousAgentDeployerUpgradeTest.sol",
      "start_line": 494,
      "end_line": 497,
      "visibility": "internal",
      "is_external": false,
      "is_payable": false
    },
    {
      "node_id": 37,
      "node_type": "function",
      "name": "pause",
      "file": "autonomous-agent-contracts_contracts_testing_AutonomousAgentDeployerUpgradeTest.sol",
      "start_line": 499,
      "end_line": 501,
      "visibility": "external",
      "is_external": true,
      "is_payable": false
    },
    {
      "node_id": 38,
      "node_type": "function",
      "name": "unpause",
      "file": "autonomous-agent-contracts_contracts_testing_AutonomousAgentDeployerUpgradeTest.sol",
      "start_line": 503,
      "end_line": 505,
      "visibility": "external",
      "is_external": true,
      "is_payable": false
    },
    {
      "node_id": 39,
      "node_type": "function",
      "name": "isAgentToken",
      "file": "autonomous-agent-contracts_contracts_testing_AutonomousAgentDeployerUpgradeTest.sol",
      "start_line": 507,
      "end_line": 509,
      "visibility": "public",
      "is_external": false,
      "is_payable": false
    },
    {
      "node_id": 40,
      "node_type": "function",
      "name": "setPauser",
      "file": "autonomous-agent-contracts_contracts_testing_AutonomousAgentDeployerUpgradeTest.sol",
      "start_line": 511,
      "end_line": 514,
      "visibility": "external",
      "is_external": true,
      "is_payable": false
    },
    {
      "node_id": 41,
      "node_type": "function",
      "name": "setDistributor",
      "file": "autonomous-agent-contracts_contracts_testing_AutonomousAgentDeployerUpgradeTest.sol",
      "start_line": 516,
      "end_line": 520,
      "visibility": "external",
      "is_external": true,
      "is_payable": false
    },
    {
      "node_id": 42,
      "node_type": "function",
      "name": "setSpectralStaking",
      "file": "autonomous-agent-contracts_contracts_testing_AutonomousAgentDeployerUpgradeTest.sol",
      "start_line": 522,
      "end_line": 526,
      "visibility": "external",
      "is_external": true,
      "is_payable": false
    },
    {
      "node_id": 43,
      "node_type": "function",
      "name": "initialize",
      "file": "autonomous-agent-contracts_contracts_testing_MockSpectralStaking.sol",
      "start_line": 132,
      "end_line": 159,
      "visibility": "public",
      "is_external": false,
      "is_payable": false
    },
    {
      "node_id": 44,
      "node_type": "function",
      "name": "setAdmin",
      "file": "autonomous-agent-contracts_contracts_testing_MockSpectralStaking.sol",
      "start_line": 161,
      "end_line": 165,
      "visibility": "external",
      "is_external": true,
      "is_payable": false
    },
    {
      "node_id": 45,
      "node_type": "function",
      "name": "addDistribution",
      "file": "autonomous-agent-contracts_contracts_testing_MockSpectralStaking.sol",
      "start_line": 168,
      "end_line": 177,
      "visibility": "external",
      "is_external": true,
      "is_payable": false
    },
    {
      "node_id": 46,
      "node_type": "function",
      "name": "addDistributionToBuffer",
      "file": "autonomous-agent-contracts_contracts_testing_MockSpectralStaking.sol",
      "start_line": 182,
      "end_line": 208,
      "visibility": "external",
      "is_external": true,
      "is_payable": false
    },
    {
      "node_id": 47,
      "node_type": "function",
      "name": "releaseDistributionBuffer",
      "file": "autonomous-agent-contracts_contracts_testing_MockSpectralStaking.sol",
      "start_line": 212,
      "end_line": 218,
      "visibility": "external",
      "is_external": true,
      "is_payable": false
    },
    {
      "node_id": 48,
      "node_type": "function",
      "name": "_releaseDistributionBuffer",
      "file": "autonomous-agent-contracts_contracts_testing_MockSpectralStaking.sol",
      "start_line": 220,
      "end_line": 232,
      "visibility": "internal",
      "is_external": false,
      "is_payable": false
    },
    {
      "node_id": 49,
      "node_type": "function",
      "name": "_addDistribution",
      "file": "autonomous-agent-contracts_contracts_testing_MockSpectralStaking.sol",
      "start_line": 234,
      "end_line": 265,
      "visibility": "internal",
      "is_external": false,
      "is_payable": false
    },
    {
      "node_id": 50,
      "node_type": "function",
      "name": "_transferDistributionRewards",
      "file": "autonomous-agent-contracts_contracts_testing_MockSpectralStaking.sol",
      "start_line": 267,
      "end_line": 292,
      "visibility": "internal",
      "is_external": false,
      "is_payable": false
    },
    {
      "node_id": 51,
      "node_type": "function",
      "name": "stake",
      "file": "autonomous-agent-contracts_contracts_testing_MockSpectralStaking.sol",
      "start_line": 295,
      "end_line": 329,
      "visibility": "external",
      "is_external": true,
      "is_payable": false
    },
    {
      "node_id": 52,
      "node_type": "function",
      "name": "withdraw",
      "file": "autonomous-agent-contracts_contracts_testing_MockSpectralStaking.sol",
      "start_line": 331,
      "end_line": 364,
      "visibility": "external",
      "is_external": true,
      "is_payable": false
    },
    {
      "node_id": 53,
      "node_type": "function",
      "name": "_claim",
      "file": "autonomous-agent-contracts_contracts_testing_MockSpectralStaking.sol",
      "start_line": 366,
      "end_line": 452,
      "visibility": "internal",
      "is_external": false,
      "is_payable": false
    },
    {
      "node_id": 54,
      "node_type": "function",
      "name": "claim",
      "file": "autonomous-agent-contracts_contracts_testing_MockSpectralStaking.sol",
      "start_line": 454,
      "end_line": 456,
      "visibility": "external",
      "is_external": true,
      "is_payable": false
    },
    {
      "node_id": 55,
      "node_type": "function",
      "name": "claimBatch",
      "file": "autonomous-agent-contracts_contracts_testing_MockSpectralStaking.sol",
      "start_line": 458,
      "end_line": 463,
      "visibility": "external",
      "is_external": true,
      "is_payable": false
    },
    {
      "node_id": 56,
      "node_type": "function",
      "name": "transferCalibration",
      "file": "autonomous-agent-contracts_contracts_testing_MockSpectralStaking.sol",
      "start_line": 465,
      "end_line": 498,
      "visibility": "external",
      "is_external": true,
      "is_payable": false
    },
    {
      "node_id": 57,
      "node_type": "function",
      "name": "setBufferBundlingPeriod",
      "file": "autonomous-agent-contracts_contracts_testing_MockSpectralStaking.sol",
      "start_line": 500,
      "end_line": 503,
      "visibility": "external",
      "is_external": true,
      "is_payable": false
    },
    {
      "node_id": 58,
      "node_type": "function",
      "name": "_authorizeUpgrade",
      "file": "autonomous-agent-contracts_contracts_testing_MockSpectralStaking.sol",
      "start_line": 505,
      "end_line": 511,
      "visibility": "internal",
      "is_external": false,
      "is_payable": false
    },
    {
      "node_id": 59,
      "node_type": "state_var",
      "name": "agentWallets",
      "var_type": "mapping (address => address) public",
      "file": "autonomous-agent-contracts_contracts_testing_AgentBalancesUpgradeTest.sol",
      "line": 16
    },
    {
      "node_id": 60,
      "node_type": "state_var",
      "name": "agentBalance",
      "var_type": "mapping (address => mapping(address => uint256)) private",
      "file": "autonomous-agent-contracts_contracts_testing_AgentBalancesUpgradeTest.sol",
      "line": 18
    },
    {
      "node_id": 61,
      "node_type": "state_var",
      "name": "agentETHBalance",
      "var_type": "mapping (address => uint256) public",
      "file": "autonomous-agent-contracts_contracts_testing_AgentBalancesUpgradeTest.sol",
      "line": 19
    },
    {
      "node_id": 62,
      "node_type": "state_var",
      "name": "admin",
      "var_type": "address public",
      "file": "autonomous-agent-contracts_contracts_testing_AgentBalancesUpgradeTest.sol",
      "line": 21
    },
    {
      "node_id": 63,
      "node_type": "state_var",
      "name": "version",
      "var_type": "uint8 public",
      "file": "autonomous-agent-contracts_contracts_testing_AgentBalancesUpgradeTest.sol",
      "line": 23
    },
    {
      "node_id": 64,
      "node_type": "state_var",
      "name": "deployer",
      "var_type": "address public",
      "file": "autonomous-agent-contracts_contracts_testing_AgentBalancesUpgradeTest.sol",
      "line": 25
    },
    {
      "node_id": 65,
      "node_type": "state_var",
      "name": "__gap",
      "var_type": "uint256[49] private",
      "file": "autonomous-agent-contracts_contracts_testing_AgentBalancesUpgradeTest.sol",
      "line": 27
    },
    {
      "node_id": 66,
      "node_type": "state_var",
      "name": "parameters",
      "var_type": "mapping(Parameter => uint256) public",
      "file": "autonomous-agent-contracts_contracts_testing_AutonomousAgentDeployerUpgradeTest.sol",
      "line": 34
    },
    {
      "node_id": 67,
      "node_type": "state_var",
      "name": "feeWallet",
      "var_type": "address payable public",
      "file": "autonomous-agent-contracts_contracts_testing_AutonomousAgentDeployerUpgradeTest.sol",
      "line": 36
    },
    {
      "node_id": 68,
      "node_type": "state_var",
      "name": "uniswapRouter",
      "var_type": "IUniswapV2Router02 public",
      "file": "autonomous-agent-contracts_contracts_testing_AutonomousAgentDeployerUpgradeTest.sol",
      "line": 38
    },
    {
      "node_id": 69,
      "node_type": "state_var",
      "name": "uniswapV3Router",
      "var_type": "ISwapRouter public",
      "file": "autonomous-agent-contracts_contracts_testing_AutonomousAgentDeployerUpgradeTest.sol",
      "line": 39
    },
    {
      "node_id": 70,
      "node_type": "state_var",
      "name": "uniswapFactory",
      "var_type": "address public",
      "file": "autonomous-agent-contracts_contracts_testing_AutonomousAgentDeployerUpgradeTest.sol",
      "line": 41
    },
    {
      "node_id": 71,
      "node_type": "state_var",
      "name": "agentTokenImplementation",
      "var_type": "address public",
      "file": "autonomous-agent-contracts_contracts_testing_AutonomousAgentDeployerUpgradeTest.sol",
      "line": 42
    },
    {
      "node_id": 72,
      "node_type": "state_var",
      "name": "UNISWAP_POOL_CREATION_VALUE",
      "var_type": "uint256 public",
      "file": "autonomous-agent-contracts_contracts_testing_AutonomousAgentDeployerUpgradeTest.sol",
      "line": 43
    },
    {
      "node_id": 73,
      "node_type": "state_var",
      "name": "spectralToken",
      "var_type": "address public",
      "file": "autonomous-agent-contracts_contracts_testing_AutonomousAgentDeployerUpgradeTest.sol",
      "line": 45
    },
    {
      "node_id": 74,
      "node_type": "state_var",
      "name": "WETH",
      "var_type": "address public",
      "file": "autonomous-agent-contracts_contracts_testing_AutonomousAgentDeployerUpgradeTest.sol",
      "line": 46
    },
    {
      "node_id": 75,
      "node_type": "state_var",
      "name": "agentBalances",
      "var_type": "IAgentBalances public",
      "file": "autonomous-agent-contracts_contracts_testing_AutonomousAgentDeployerUpgradeTest.sol",
      "line": 47
    },
    {
      "node_id": 76,
      "node_type": "state_var",
      "name": "agentTokens",
      "var_type": "mapping (address => bool) public",
      "file": "autonomous-agent-contracts_contracts_testing_AutonomousAgentDeployerUpgradeTest.sol",
      "line": 49
    },
    {
      "node_id": 77,
      "node_type": "state_var",
      "name": "agentTokensSold",
      "var_type": "mapping (address => uint256) public",
      "file": "autonomous-agent-contracts_contracts_testing_AutonomousAgentDeployerUpgradeTest.sol",
      "line": 50
    },
    {
      "node_id": 78,
      "node_type": "state_var",
      "name": "agentWallets",
      "var_type": "mapping (address => address) public",
      "file": "autonomous-agent-contracts_contracts_testing_AutonomousAgentDeployerUpgradeTest.sol",
      "line": 51
    },
    {
      "node_id": 79,
      "node_type": "state_var",
      "name": "totalSPECDeposited",
      "var_type": "mapping (address => uint256) public",
      "file": "autonomous-agent-contracts_contracts_testing_AutonomousAgentDeployerUpgradeTest.sol",
      "line": 52
    },
    {
      "node_id": 80,
      "node_type": "state_var",
      "name": "agentTokenUniswapPool",
      "var_type": "mapping (address => address) public",
      "file": "autonomous-agent-contracts_contracts_testing_AutonomousAgentDeployerUpgradeTest.sol",
      "line": 53
    },
    {
      "node_id": 81,
      "node_type": "state_var",
      "name": "admin",
      "var_type": "address public",
      "file": "autonomous-agent-contracts_contracts_testing_AutonomousAgentDeployerUpgradeTest.sol",
      "line": 55
    },
    {
      "node_id": 82,
      "node_type": "state_var",
      "name": "version",
      "var_type": "uint8 public",
      "file": "autonomous-agent-contracts_contracts_testing_AutonomousAgentDeployerUpgradeTest.sol",
      "line": 57
    },
    {
      "node_id": 83,
      "node_type": "state_var",
      "name": "agentsVersion",
      "var_type": "uint8 public",
      "file": "autonomous-agent-contracts_contracts_testing_AutonomousAgentDeployerUpgradeTest.sol",
      "line": 58
    },
    {
      "node_id": 84,
      "node_type": "state_var",
      "name": "paused",
      "var_type": "bool public",
      "file": "autonomous-agent-contracts_contracts_testing_AutonomousAgentDeployerUpgradeTest.sol",
      "line": 60
    },
    {
      "node_id": 85,
      "node_type": "state_var",
      "name": "pauser",
      "var_type": "address public",
      "file": "autonomous-agent-contracts_contracts_testing_AutonomousAgentDeployerUpgradeTest.sol",
      "line": 61
    },
    {
      "node_id": 86,
      "node_type": "state_var",
      "name": "INITIAL_VIRTUAL_LIQUIDITY",
      "var_type": "uint256 constant",
      "file": "autonomous-agent-contracts_contracts_testing_AutonomousAgentDeployerUpgradeTest.sol",
      "line": 63
    },
    {
      "node_id": 87,
      "node_type": "state_var",
      "name": "distributor",
      "var_type": "IOctoDistributor public",
      "file": "autonomous-agent-contracts_contracts_testing_AutonomousAgentDeployerUpgradeTest.sol",
      "line": 65
    },
    {
      "node_id": 88,
      "node_type": "state_var",
      "name": "spectralStaking",
      "var_type": "ISpectralStaking public",
      "file": "autonomous-agent-contracts_contracts_testing_AutonomousAgentDeployerUpgradeTest.sol",
      "line": 66
    },
    {
      "node_id": 89,
      "node_type": "state_var",
      "name": "accumulatedTaxToSwap",
      "var_type": "uint256 public",
      "file": "autonomous-agent-contracts_contracts_testing_AutonomousAgentDeployerUpgradeTest.sol",
      "line": 67
    },
    {
      "node_id": 90,
      "node_type": "state_var",
      "name": "accumulatedTaxToSwapByAgent",
      "var_type": "mapping(address => uint256) public",
      "file": "autonomous-agent-contracts_contracts_testing_AutonomousAgentDeployerUpgradeTest.sol",
      "line": 68
    },
    {
      "node_id": 91,
      "node_type": "state_var",
      "name": "__gap",
      "var_type": "uint256[44] private",
      "file": "autonomous-agent-contracts_contracts_testing_AutonomousAgentDeployerUpgradeTest.sol",
      "line": 70
    },
    {
      "node_id": 92,
      "node_type": "state_var",
      "name": "spectralToken",
      "var_type": "IERC20Upgradeable public",
      "file": "autonomous-agent-contracts_contracts_testing_MockSpectralStaking.sol",
      "line": 25
    },
    {
      "node_id": 93,
      "node_type": "state_var",
      "name": "stakingToken",
      "var_type": "ISpectralStakingToken public",
      "file": "autonomous-agent-contracts_contracts_testing_MockSpectralStaking.sol",
      "line": 26
    },
    {
      "node_id": 94,
      "node_type": "state_var",
      "name": "admin",
      "var_type": "address public",
      "file": "autonomous-agent-contracts_contracts_testing_MockSpectralStaking.sol",
      "line": 27
    },
    {
      "node_id": 95,
      "node_type": "state_var",
      "name": "version",
      "var_type": "uint8",
      "file": "autonomous-agent-contracts_contracts_testing_MockSpectralStaking.sol",
      "line": 28
    },
    {
      "node_id": 96,
      "node_type": "state_var",
      "name": "totalStaked",
      "var_type": "uint256 public",
      "file": "autonomous-agent-contracts_contracts_testing_MockSpectralStaking.sol",
      "line": 31
    },
    {
      "node_id": 97,
      "node_type": "state_var",
      "name": "totalDebtWeight",
      "var_type": "int256 public",
      "file": "autonomous-agent-contracts_contracts_testing_MockSpectralStaking.sol",
      "line": 32
    },
    {
      "node_id": 98,
      "node_type": "state_var",
      "name": "distributionCount",
      "var_type": "uint256 public",
      "file": "autonomous-agent-contracts_contracts_testing_MockSpectralStaking.sol",
      "line": 33
    },
    {
      "node_id": 99,
      "node_type": "state_var",
      "name": "distributionBufferBundlingPeriod",
      "var_type": "uint256 public",
      "file": "autonomous-agent-contracts_contracts_testing_MockSpectralStaking.sol",
      "line": 34
    },
    {
      "node_id": 100,
      "node_type": "state_var",
      "name": "PRECISION",
      "var_type": "uint256 private constant",
      "file": "autonomous-agent-contracts_contracts_testing_MockSpectralStaking.sol",
      "line": 37
    },
    {
      "node_id": 101,
      "node_type": "state_var",
      "name": "CLAIM_WITHDRAW_DELAY",
      "var_type": "uint256 public constant",
      "file": "autonomous-agent-contracts_contracts_testing_MockSpectralStaking.sol",
      "line": 38
    },
    {
      "node_id": 102,
      "node_type": "state_var",
      "name": "lastDeposit",
      "var_type": "mapping(address => uint256) public",
      "file": "autonomous-agent-contracts_contracts_testing_MockSpectralStaking.sol",
      "line": 68
    },
    {
      "node_id": 103,
      "node_type": "state_var",
      "name": "lastClaimedIndex",
      "var_type": "mapping(address => uint256) public",
      "file": "autonomous-agent-contracts_contracts_testing_MockSpectralStaking.sol",
      "line": 70
    },
    {
      "node_id": 104,
      "node_type": "state_var",
      "name": "distributions",
      "var_type": "mapping(uint256 => DistributionInfo) public",
      "file": "autonomous-agent-contracts_contracts_testing_MockSpectralStaking.sol",
      "line": 72
    },
    {
      "node_id": 105,
      "node_type": "state_var",
      "name": "userDistributions",
      "var_type": "mapping(uint256 => mapping(address => UserDistributionInfo)) public",
      "file": "autonomous-agent-contracts_contracts_testing_MockSpectralStaking.sol",
      "line": 74
    },
    {
      "node_id": 106,
      "node_type": "state_var",
      "name": "distributionBuffer",
      "var_type": "mapping(address => mapping (address => DistributionBufferInfo)) public",
      "file": "autonomous-agent-contracts_contracts_testing_MockSpectralStaking.sol",
      "line": 76
    },
    {
      "node_id": 107,
      "node_type": "state_var",
      "name": "deployer",
      "var_type": "address public",
      "file": "autonomous-agent-contracts_contracts_testing_MockSpectralStaking.sol",
      "line": 79
    },
    {
      "node_id": 108,
      "node_type": "state_var",
      "name": "__gap",
      "var_type": "uint256[49] private",
      "file": "autonomous-agent-contracts_contracts_testing_MockSpectralStaking.sol",
      "line": 82
    },
    {
      "node_id": 109,
      "node_type": "call_site",
      "name": "TRANSFER:autonomous-agent-contracts_contracts_testing_AgentBalancesUpgradeTest.sol:92",
      "call_type": "TRANSFER",
      "line": 92,
      "enclosing_function": "withdrawETH",
      "file": "autonomous-agent-contracts_contracts_testing_AgentBalancesUpgradeTest.sol",
      "raw_text": "payable(msg.sender).transfer(amount);"
    },
    {
      "node_id": 110,
      "node_type": "call_site",
      "name": "TRANSFER:autonomous-agent-contracts_contracts_testing_AgentBalancesUpgradeTest.sol:115",
      "call_type": "TRANSFER",
      "line": 115,
      "enclosing_function": "depositETH",
      "file": "autonomous-agent-contracts_contracts_testing_AgentBalancesUpgradeTest.sol",
      "raw_text": "payable(agentWallets[agent]).transfer(msg.value);"
    },
    {
      "node_id": 111,
      "node_type": "call_site",
      "name": "TRANSFER:autonomous-agent-contracts_contracts_testing_AgentBalancesUpgradeTest.sol:136",
      "call_type": "TRANSFER",
      "line": 136,
      "enclosing_function": "claimETHForAgent",
      "file": "autonomous-agent-contracts_contracts_testing_AgentBalancesUpgradeTest.sol",
      "raw_text": "payable(agentWallets[agent]).transfer(amount);"
    },
    {
      "node_id": 112,
      "node_type": "call_site",
      "name": "TRANSFER:autonomous-agent-contracts_contracts_testing_AutonomousAgentDeployerUpgradeTest.sol:169",
      "call_type": "TRANSFER",
      "line": 169,
      "enclosing_function": "deployAgent",
      "file": "autonomous-agent-contracts_contracts_testing_AutonomousAgentDeployerUpgradeTest.sol",
      "raw_text": "IERC20Upgradeable(_agentToken).transfer(msg.sender, creatorTokensReceived);"
    },
    {
      "node_id": 113,
      "node_type": "call_site",
      "name": "TRANSFER:autonomous-agent-contracts_contracts_testing_AutonomousAgentDeployerUpgradeTest.sol:203",
      "call_type": "TRANSFER",
      "line": 203,
      "enclosing_function": "deployAgentWithETH",
      "file": "autonomous-agent-contracts_contracts_testing_AutonomousAgentDeployerUpgradeTest.sol",
      "raw_text": "IERC20Upgradeable(_agentToken).transfer(msg.sender, creatorTokensReceived);"
    },
    {
      "node_id": 114,
      "node_type": "call_site",
      "name": "INTERFACE_CALL:autonomous-agent-contracts_contracts_testing_AutonomousAgentDeployerUpgradeTest.sol:226",
      "call_type": "INTERFACE_CALL",
      "line": 226,
      "enclosing_function": "initializeAgent",
      "file": "autonomous-agent-contracts_contracts_testing_AutonomousAgentDeployerUpgradeTest.sol",
      "raw_text": "distributor.setAgentCreator(_agentToken, msg.sender);"
    },
    {
      "node_id": 115,
      "node_type": "call_site",
      "name": "TRANSFER:autonomous-agent-contracts_contracts_testing_AutonomousAgentDeployerUpgradeTest.sol:228",
      "call_type": "TRANSFER",
      "line": 228,
      "enclosing_function": "initializeAgent",
      "file": "autonomous-agent-contracts_contracts_testing_AutonomousAgentDeployerUpgradeTest.sol",
      "raw_text": "IERC20Upgradeable(_agentToken).transfer(feeWallet, parameters[Parameter.AGENT_TOKEN_DEPLOYMENT_FEE]);"
    },
    {
      "node_id": 116,
      "node_type": "call_site",
      "name": "INTERFACE_CALL:autonomous-agent-contracts_contracts_testing_AutonomousAgentDeployerUpgradeTest.sol:231",
      "call_type": "INTERFACE_CALL",
      "line": 231,
      "enclosing_function": "initializeAgent",
      "file": "autonomous-agent-contracts_contracts_testing_AutonomousAgentDeployerUpgradeTest.sol",
      "raw_text": "spectralStaking.addDistribution(_agentToken, address(0), 2_000_000 ether, 0);"
    },
    {
      "node_id": 117,
      "node_type": "call_site",
      "name": "INTERFACE_CALL:autonomous-agent-contracts_contracts_testing_AutonomousAgentDeployerUpgradeTest.sol:234",
      "call_type": "INTERFACE_CALL",
      "line": 234,
      "enclosing_function": "initializeAgent",
      "file": "autonomous-agent-contracts_contracts_testing_AutonomousAgentDeployerUpgradeTest.sol",
      "raw_text": "agentBalances.deposit(address(this), _agentToken, _agentToken, parameters[Parameter.AGENT_TOKEN_OWNERSHIP]);"
    },
    {
      "node_id": 118,
      "node_type": "call_site",
      "name": "CALL:autonomous-agent-contracts_contracts_testing_AutonomousAgentDeployerUpgradeTest.sol:239",
      "call_type": "CALL",
      "line": 239,
      "enclosing_function": "initializeAgent",
      "file": "autonomous-agent-contracts_contracts_testing_AutonomousAgentDeployerUpgradeTest.sol",
      "raw_text": "(bool success, ) = feeWallet.call{value: parameters[Parameter.DEPLOYMENT_TREASURY_FEE]}(\"\");"
    },
    {
      "node_id": 119,
      "node_type": "call_site",
      "name": "INTERFACE_CALL:autonomous-agent-contracts_contracts_testing_AutonomousAgentDeployerUpgradeTest.sol:243",
      "call_type": "INTERFACE_CALL",
      "line": 243,
      "enclosing_function": "initializeAgent",
      "file": "autonomous-agent-contracts_contracts_testing_AutonomousAgentDeployerUpgradeTest.sol",
      "raw_text": "agentBalances.depositETH{value: parameters[Parameter.INITIAL_TRADING_BALANCE]}(_agentToken);"
    },
    {
      "node_id": 120,
      "node_type": "call_site",
      "name": "INTERFACE_CALL:autonomous-agent-contracts_contracts_testing_AutonomousAgentDeployerUpgradeTest.sol:273",
      "call_type": "INTERFACE_CALL",
      "line": 273,
      "enclosing_function": "swapETHForSPEC",
      "file": "autonomous-agent-contracts_contracts_testing_AutonomousAgentDeployerUpgradeTest.sol",
      "raw_text": "specAmount = uniswapV3Router.exactInputSingle{value: ethAmount}(params);"
    },
    {
      "node_id": 121,
      "node_type": "call_site",
      "name": "INTERFACE_CALL:autonomous-agent-contracts_contracts_testing_AutonomousAgentDeployerUpgradeTest.sol:302",
      "call_type": "INTERFACE_CALL",
      "line": 302,
      "enclosing_function": "_getTokensFromUniswap",
      "file": "autonomous-agent-contracts_contracts_testing_AutonomousAgentDeployerUpgradeTest.sol",
      "raw_text": "uint256[] memory amounts = uniswapRouter.getAmountsOut(_amountIn, path);"
    },
    {
      "node_id": 122,
      "node_type": "call_site",
      "name": "INTERFACE_CALL:autonomous-agent-contracts_contracts_testing_AutonomousAgentDeployerUpgradeTest.sol:348",
      "call_type": "INTERFACE_CALL",
      "line": 348,
      "enclosing_function": "swapExactSPECForTokens",
      "file": "autonomous-agent-contracts_contracts_testing_AutonomousAgentDeployerUpgradeTest.sol",
      "raw_text": "uniswapRouter.swapExactTokensForTokensSupportingFeeOnTransferTokens(userSpecAmount, amountOutMin, path, msg.sender, _deadline);"
    },
    {
      "node_id": 123,
      "node_type": "call_site",
      "name": "INTERFACE_CALL:autonomous-agent-contracts_contracts_testing_AutonomousAgentDeployerUpgradeTest.sol:366",
      "call_type": "INTERFACE_CALL",
      "line": 366,
      "enclosing_function": "swapExactSPECForTokens",
      "file": "autonomous-agent-contracts_contracts_testing_AutonomousAgentDeployerUpgradeTest.sol",
      "raw_text": "uniswapRouter.addLiquidity("
    },
    {
      "node_id": 124,
      "node_type": "call_site",
      "name": "INTERFACE_CALL:autonomous-agent-contracts_contracts_testing_AutonomousAgentDeployerUpgradeTest.sol:396",
      "call_type": "INTERFACE_CALL",
      "line": 396,
      "enclosing_function": "swapExactTokensForSPEC",
      "file": "autonomous-agent-contracts_contracts_testing_AutonomousAgentDeployerUpgradeTest.sol",
      "raw_text": "uniswapRouter.swapExactTokensForTokensSupportingFeeOnTransferTokens(userSwapAfterTax, amountOutMin, path, msg.sender, deadline);"
    },
    {
      "node_id": 125,
      "node_type": "call_site",
      "name": "INTERFACE_CALL:autonomous-agent-contracts_contracts_testing_AutonomousAgentDeployerUpgradeTest.sol:402",
      "call_type": "INTERFACE_CALL",
      "line": 402,
      "enclosing_function": "swapExactTokensForSPEC",
      "file": "autonomous-agent-contracts_contracts_testing_AutonomousAgentDeployerUpgradeTest.sol",
      "raw_text": "uniswapRouter.swapExactTokensForTokensSupportingFeeOnTransferTokens(protocolSwapAmount, (protocolSpecAmount * 80) / 100, path, address(this), deadline);"
    },
    {
      "node_id": 126,
      "node_type": "call_site",
      "name": "TRANSFER:autonomous-agent-contracts_contracts_testing_AutonomousAgentDeployerUpgradeTest.sol:430",
      "call_type": "TRANSFER",
      "line": 430,
      "enclosing_function": "_distributeSwapFees",
      "file": "autonomous-agent-contracts_contracts_testing_AutonomousAgentDeployerUpgradeTest.sol",
      "raw_text": "IERC20(spectralToken).transfer(feeWallet, splitAmount);"
    },
    {
      "node_id": 127,
      "node_type": "call_site",
      "name": "INTERFACE_CALL:autonomous-agent-contracts_contracts_testing_AutonomousAgentDeployerUpgradeTest.sol:432",
      "call_type": "INTERFACE_CALL",
      "line": 432,
      "enclosing_function": "_distributeSwapFees",
      "file": "autonomous-agent-contracts_contracts_testing_AutonomousAgentDeployerUpgradeTest.sol",
      "raw_text": "spectralStaking.addDistributionToBuffer(spectralToken, address(0), splitAmount, 0);"
    },
    {
      "node_id": 128,
      "node_type": "call_site",
      "name": "CALL:autonomous-agent-contracts_contracts_testing_AutonomousAgentDeployerUpgradeTest.sol:455",
      "call_type": "CALL",
      "line": 455,
      "enclosing_function": "withdrawEther",
      "file": "autonomous-agent-contracts_contracts_testing_AutonomousAgentDeployerUpgradeTest.sol",
      "raw_text": "(bool success, ) = payable(owner()).call{value: amount}(\"\");"
    },
    {
      "node_id": 129,
      "node_type": "call_site",
      "name": "INTERFACE_CALL:autonomous-agent-contracts_contracts_testing_MockSpectralStaking.sol:298",
      "call_type": "INTERFACE_CALL",
      "line": 298,
      "enclosing_function": "stake",
      "file": "autonomous-agent-contracts_contracts_testing_MockSpectralStaking.sol",
      "raw_text": "spectralToken.safeTransferFrom(msg.sender, address(this), amount);"
    },
    {
      "node_id": 130,
      "node_type": "call_site",
      "name": "INTERFACE_CALL:autonomous-agent-contracts_contracts_testing_MockSpectralStaking.sol:317",
      "call_type": "INTERFACE_CALL",
      "line": 317,
      "enclosing_function": "stake",
      "file": "autonomous-agent-contracts_contracts_testing_MockSpectralStaking.sol",
      "raw_text": "stakingToken.mint(msg.sender, amount);"
    },
    {
      "node_id": 131,
      "node_type": "call_site",
      "name": "INTERFACE_CALL:autonomous-agent-contracts_contracts_testing_MockSpectralStaking.sol:338",
      "call_type": "INTERFACE_CALL",
      "line": 338,
      "enclosing_function": "withdraw",
      "file": "autonomous-agent-contracts_contracts_testing_MockSpectralStaking.sol",
      "raw_text": "stakingToken.balanceOf(msg.sender) >= amount,"
    },
    {
      "node_id": 132,
      "node_type": "call_site",
      "name": "INTERFACE_CALL:autonomous-agent-contracts_contracts_testing_MockSpectralStaking.sol:359",
      "call_type": "INTERFACE_CALL",
      "line": 359,
      "enclosing_function": "withdraw",
      "file": "autonomous-agent-contracts_contracts_testing_MockSpectralStaking.sol",
      "raw_text": "stakingToken.burn(msg.sender, amount);"
    },
    {
      "node_id": 133,
      "node_type": "call_site",
      "name": "INTERFACE_CALL:autonomous-agent-contracts_contracts_testing_MockSpectralStaking.sol:361",
      "call_type": "INTERFACE_CALL",
      "line": 361,
      "enclosing_function": "withdraw",
      "file": "autonomous-agent-contracts_contracts_testing_MockSpectralStaking.sol",
      "raw_text": "spectralToken.safeTransfer(msg.sender, amount);"
    },
    {
      "node_id": 134,
      "node_type": "call_site",
      "name": "TRANSFER:autonomous-agent-contracts_contracts_testing_MockSpectralStaking.sol:434",
      "call_type": "TRANSFER",
      "line": 434,
      "enclosing_function": "_claim",
      "file": "autonomous-agent-contracts_contracts_testing_MockSpectralStaking.sol",
      "raw_text": "IERC20Upgradeable(rewardTokenA).transfer("
    },
    {
      "node_id": 135,
      "node_type": "call_site",
      "name": "TRANSFER:autonomous-agent-contracts_contracts_testing_MockSpectralStaking.sol:441",
      "call_type": "TRANSFER",
      "line": 441,
      "enclosing_function": "_claim",
      "file": "autonomous-agent-contracts_contracts_testing_MockSpectralStaking.sol",
      "raw_text": "IERC20Upgradeable(rewardTokenB).transfer("
    },
    {
      "node_id": 136,
      "node_type": "call_site",
      "name": "INTERFACE_CALL:autonomous-agent-contracts_contracts_testing_MockSpectralStaking.sol:468",
      "call_type": "INTERFACE_CALL",
      "line": 468,
      "enclosing_function": "transferCalibration",
      "file": "autonomous-agent-contracts_contracts_testing_MockSpectralStaking.sol",
      "raw_text": "stakingToken.balanceOf(_from) >= amount,"
    }
  ],
  "hyperedges": [
    {
      "edge_id": 0,
      "node_ids": [
        5,
        59,
        61,
        109
      ],
      "tau": "TRANSFER",
      "anchor_call_site_id": 109
    },
    {
      "edge_id": 1,
      "node_ids": [
        7,
        59,
        61,
        110
      ],
      "tau": "TRANSFER",
      "anchor_call_site_id": 110
    },
    {
      "edge_id": 2,
      "node_ids": [
        9,
        59,
        61,
        111
      ],
      "tau": "TRANSFER",
      "anchor_call_site_id": 111
    },
    {
      "edge_id": 3,
      "node_ids": [
        14,
        66,
        73,
        112
      ],
      "tau": "TRANSFER",
      "anchor_call_site_id": 112
    },
    {
      "edge_id": 4,
      "node_ids": [
        15,
        66,
        113
      ],
      "tau": "TRANSFER",
      "anchor_call_site_id": 113
    },
    {
      "edge_id": 5,
      "node_ids": [
        14,
        15,
        16,
        66,
        67,
        71,
        73,
        75,
        76,
        77,
        79,
        87,
        88,
        114
      ],
      "tau": "INTERFACE_CALL",
      "anchor_call_site_id": 114
    },
    {
      "edge_id": 6,
      "node_ids": [
        14,
        15,
        16,
        66,
        67,
        71,
        73,
        75,
        76,
        77,
        79,
        87,
        88,
        115
      ],
      "tau": "TRANSFER",
      "anchor_call_site_id": 115
    },
    {
      "edge_id": 7,
      "node_ids": [
        14,
        15,
        16,
        66,
        67,
        71,
        73,
        75,
        76,
        77,
        79,
        87,
        88,
        116
      ],
      "tau": "INTERFACE_CALL",
      "anchor_call_site_id": 116
    },
    {
      "edge_id": 8,
      "node_ids": [
        14,
        15,
        16,
        66,
        67,
        71,
        73,
        75,
        76,
        77,
        79,
        87,
        88,
        117
      ],
      "tau": "INTERFACE_CALL",
      "anchor_call_site_id": 117
    },
    {
      "edge_id": 9,
      "node_ids": [
        14,
        15,
        16,
        66,
        67,
        71,
        73,
        75,
        76,
        77,
        79,
        87,
        88,
        118
      ],
      "tau": "CALL",
      "anchor_call_site_id": 118
    },
    {
      "edge_id": 10,
      "node_ids": [
        14,
        15,
        16,
        66,
        67,
        71,
        73,
        75,
        76,
        77,
        79,
        87,
        88,
        119
      ],
      "tau": "INTERFACE_CALL",
      "anchor_call_site_id": 119
    },
    {
      "edge_id": 11,
      "node_ids": [
        15,
        17,
        66,
        69,
        73,
        74,
        120
      ],
      "tau": "INTERFACE_CALL",
      "anchor_call_site_id": 120
    },
    {
      "edge_id": 12,
      "node_ids": [
        14,
        15,
        16,
        18,
        19,
        20,
        22,
        23,
        24,
        66,
        67,
        68,
        71,
        72,
        73,
        75,
        76,
        77,
        79,
        80,
        87,
        88,
        90,
        121
      ],
      "tau": "INTERFACE_CALL",
      "anchor_call_site_id": 121
    },
    {
      "edge_id": 13,
      "node_ids": [
        23,
        68,
        72,
        73,
        75,
        76,
        77,
        79,
        80,
        122
      ],
      "tau": "INTERFACE_CALL",
      "anchor_call_site_id": 122
    },
    {
      "edge_id": 14,
      "node_ids": [
        23,
        68,
        72,
        73,
        75,
        76,
        77,
        79,
        80,
        123
      ],
      "tau": "INTERFACE_CALL",
      "anchor_call_site_id": 123
    },
    {
      "edge_id": 15,
      "node_ids": [
        24,
        68,
        73,
        76,
        77,
        79,
        80,
        90,
        124
      ],
      "tau": "INTERFACE_CALL",
      "anchor_call_site_id": 124
    },
    {
      "edge_id": 16,
      "node_ids": [
        24,
        68,
        73,
        76,
        77,
        79,
        80,
        90,
        125
      ],
      "tau": "INTERFACE_CALL",
      "anchor_call_site_id": 125
    },
    {
      "edge_id": 17,
      "node_ids": [
        23,
        24,
        26,
        67,
        68,
        72,
        73,
        75,
        76,
        77,
        79,
        80,
        88,
        90,
        126
      ],
      "tau": "TRANSFER",
      "anchor_call_site_id": 126
    },
    {
      "edge_id": 18,
      "node_ids": [
        23,
        24,
        26,
        67,
        68,
        72,
        73,
        75,
        76,
        77,
        79,
        80,
        88,
        90,
        127
      ],
      "tau": "INTERFACE_CALL",
      "anchor_call_site_id": 127
    },
    {
      "edge_id": 19,
      "node_ids": [
        29,
        128
      ],
      "tau": "CALL",
      "anchor_call_site_id": 128
    },
    {
      "edge_id": 20,
      "node_ids": [
        51,
        73,
        93,
        96,
        97,
        98,
        102,
        103,
        104,
        105,
        129
      ],
      "tau": "INTERFACE_CALL",
      "anchor_call_site_id": 129
    },
    {
      "edge_id": 21,
      "node_ids": [
        51,
        73,
        93,
        96,
        97,
        98,
        102,
        103,
        104,
        105,
        130
      ],
      "tau": "INTERFACE_CALL",
      "anchor_call_site_id": 130
    },
    {
      "edge_id": 22,
      "node_ids": [
        4,
        59,
        60,
        73,
        93,
        96,
        97,
        98,
        101,
        102,
        104,
        105,
        131
      ],
      "tau": "INTERFACE_CALL",
      "anchor_call_site_id": 131
    },
    {
      "edge_id": 23,
      "node_ids": [
        4,
        59,
        60,
        73,
        93,
        96,
        97,
        98,
        101,
        102,
        104,
        105,
        132
      ],
      "tau": "INTERFACE_CALL",
      "anchor_call_site_id": 132
    },
    {
      "edge_id": 24,
      "node_ids": [
        4,
        59,
        60,
        73,
        93,
        96,
        97,
        98,
        101,
        102,
        104,
        105,
        133
      ],
      "tau": "INTERFACE_CALL",
      "anchor_call_site_id": 133
    },
    {
      "edge_id": 25,
      "node_ids": [
        53,
        54,
        55,
        96,
        98,
        100,
        101,
        102,
        103,
        104,
        105,
        134
      ],
      "tau": "TRANSFER",
      "anchor_call_site_id": 134
    },
    {
      "edge_id": 26,
      "node_ids": [
        53,
        54,
        55,
        96,
        98,
        100,
        101,
        102,
        103,
        104,
        105,
        135
      ],
      "tau": "TRANSFER",
      "anchor_call_site_id": 135
    },
    {
      "edge_id": 27,
      "node_ids": [
        56,
        93,
        98,
        102,
        103,
        104,
        105,
        136
      ],
      "tau": "INTERFACE_CALL",
      "anchor_call_site_id": 136
    }
  ],
  "node_features_raw": [
    {
      "node_id": 0,
      "node_type": "function",
      "name": "initialize",
      "file": "autonomous-agent-contracts_contracts_testing_AgentBalancesUpgradeTest.sol"
    },
    {
      "node_id": 1,
      "node_type": "function",
      "name": "setAdmin",
      "file": "autonomous-agent-contracts_contracts_testing_AgentBalancesUpgradeTest.sol"
    },
    {
      "node_id": 2,
      "node_type": "function",
      "name": "setDeployer",
      "file": "autonomous-agent-contracts_contracts_testing_AgentBalancesUpgradeTest.sol"
    },
    {
      "node_id": 3,
      "node_type": "function",
      "name": "setAgentWallet",
      "file": "autonomous-agent-contracts_contracts_testing_AgentBalancesUpgradeTest.sol"
    },
    {
      "node_id": 4,
      "node_type": "function",
      "name": "withdraw",
      "file": "autonomous-agent-contracts_contracts_testing_AgentBalancesUpgradeTest.sol"
    },
    {
      "node_id": 5,
      "node_type": "function",
      "name": "withdrawETH",
      "file": "autonomous-agent-contracts_contracts_testing_AgentBalancesUpgradeTest.sol"
    },
    {
      "node_id": 6,
      "node_type": "function",
      "name": "deposit",
      "file": "autonomous-agent-contracts_contracts_testing_AgentBalancesUpgradeTest.sol"
    },
    {
      "node_id": 7,
      "node_type": "function",
      "name": "depositETH",
      "file": "autonomous-agent-contracts_contracts_testing_AgentBalancesUpgradeTest.sol"
    },
    {
      "node_id": 8,
      "node_type": "function",
      "name": "claimForAgent",
      "file": "autonomous-agent-contracts_contracts_testing_AgentBalancesUpgradeTest.sol"
    },
    {
      "node_id": 9,
      "node_type": "function",
      "name": "claimETHForAgent",
      "file": "autonomous-agent-contracts_contracts_testing_AgentBalancesUpgradeTest.sol"
    },
    {
      "node_id": 10,
      "node_type": "function",
      "name": "getLPBalance",
      "file": "autonomous-agent-contracts_contracts_testing_AgentBalancesUpgradeTest.sol"
    },
    {
      "node_id": 11,
      "node_type": "function",
      "name": "getAgentBalance",
      "file": "autonomous-agent-contracts_contracts_testing_AgentBalancesUpgradeTest.sol"
    },
    {
      "node_id": 12,
      "node_type": "function",
      "name": "_authorizeUpgrade",
      "file": "autonomous-agent-contracts_contracts_testing_AgentBalancesUpgradeTest.sol"
    },
    {
      "node_id": 13,
      "node_type": "function",
      "name": "initialize",
      "file": "autonomous-agent-contracts_contracts_testing_AutonomousAgentDeployerUpgradeTest.sol"
    },
    {
      "node_id": 14,
      "node_type": "function",
      "name": "deployAgent",
      "file": "autonomous-agent-contracts_contracts_testing_AutonomousAgentDeployerUpgradeTest.sol"
    },
    {
      "node_id": 15,
      "node_type": "function",
      "name": "deployAgentWithETH",
      "file": "autonomous-agent-contracts_contracts_testing_AutonomousAgentDeployerUpgradeTest.sol"
    },
    {
      "node_id": 16,
      "node_type": "function",
      "name": "initializeAgent",
      "file": "autonomous-agent-contracts_contracts_testing_AutonomousAgentDeployerUpgradeTest.sol"
    },
    {
      "node_id": 17,
      "node_type": "function",
      "name": "swapETHForSPEC",
      "file": "autonomous-agent-contracts_contracts_testing_AutonomousAgentDeployerUpgradeTest.sol"
    },
    {
      "node_id": 18,
      "node_type": "function",
      "name": "getTokensReceived",
      "file": "autonomous-agent-contracts_contracts_testing_AutonomousAgentDeployerUpgradeTest.sol"
    },
    {
      "node_id": 19,
      "node_type": "function",
      "name": "getSPECReceived",
      "file": "autonomous-agent-contracts_contracts_testing_AutonomousAgentDeployerUpgradeTest.sol"
    },
    {
      "node_id": 20,
      "node_type": "function",
      "name": "_getTokensFromUniswap",
      "file": "autonomous-agent-contracts_contracts_testing_AutonomousAgentDeployerUpgradeTest.sol"
    },
    {
      "node_id": 21,
      "node_type": "function",
      "name": "_getTokensFromBondingCurve",
      "file": "autonomous-agent-contracts_contracts_testing_AutonomousAgentDeployerUpgradeTest.sol"
    },
    {
      "node_id": 22,
      "node_type": "function",
      "name": "getSPECAmountForTokens",
      "file": "autonomous-agent-contracts_contracts_testing_AutonomousAgentDeployerUpgradeTest.sol"
    },
    {
      "node_id": 23,
      "node_type": "function",
      "name": "swapExactSPECForTokens",
      "file": "autonomous-agent-contracts_contracts_testing_AutonomousAgentDeployerUpgradeTest.sol"
    },
    {
      "node_id": 24,
      "node_type": "function",
      "name": "swapExactTokensForSPEC",
      "file": "autonomous-agent-contracts_contracts_testing_AutonomousAgentDeployerUpgradeTest.sol"
    },
    {
      "node_id": 25,
      "node_type": "function",
      "name": "accumulateSwapFees",
      "file": "autonomous-agent-contracts_contracts_testing_AutonomousAgentDeployerUpgradeTest.sol"
    },
    {
      "node_id": 26,
      "node_type": "function",
      "name": "_distributeSwapFees",
      "file": "autonomous-agent-contracts_contracts_testing_AutonomousAgentDeployerUpgradeTest.sol"
    },
    {
      "node_id": 27,
      "node_type": "function",
      "name": "deployUniswapPool",
      "file": "autonomous-agent-contracts_contracts_testing_AutonomousAgentDeployerUpgradeTest.sol"
    },
    {
      "node_id": 28,
      "node_type": "function",
      "name": "withdrawTokens",
      "file": "autonomous-agent-contracts_contracts_testing_AutonomousAgentDeployerUpgradeTest.sol"
    },
    {
      "node_id": 29,
      "node_type": "function",
      "name": "withdrawEther",
      "file": "autonomous-agent-contracts_contracts_testing_AutonomousAgentDeployerUpgradeTest.sol"
    },
    {
      "node_id": 30,
      "node_type": "function",
      "name": "setParameter",
      "file": "autonomous-agent-contracts_contracts_testing_AutonomousAgentDeployerUpgradeTest.sol"
    },
    {
      "node_id": 31,
      "node_type": "function",
      "name": "addAlreadyExistingUniswapPool",
      "file": "autonomous-agent-contracts_contracts_testing_AutonomousAgentDeployerUpgradeTest.sol"
    },
    {
      "node_id": 32,
      "node_type": "function",
      "name": "setFeeWallet",
      "file": "autonomous-agent-contracts_contracts_testing_AutonomousAgentDeployerUpgradeTest.sol"
    },
    {
      "node_id": 33,
      "node_type": "function",
      "name": "setAdmin",
      "file": "autonomous-agent-contracts_contracts_testing_AutonomousAgentDeployerUpgradeTest.sol"
    },
    {
      "node_id": 34,
      "node_type": "function",
      "name": "changePoolCreationValue",
      "file": "autonomous-agent-contracts_contracts_testing_AutonomousAgentDeployerUpgradeTest.sol"
    },
    {
      "node_id": 35,
      "node_type": "function",
      "name": "upgradeAllAgents",
      "file": "autonomous-agent-contracts_contracts_testing_AutonomousAgentDeployerUpgradeTest.sol"
    },
    {
      "node_id": 36,
      "node_type": "function",
      "name": "_authorizeUpgrade",
      "file": "autonomous-agent-contracts_contracts_testing_AutonomousAgentDeployerUpgradeTest.sol"
    },
    {
      "node_id": 37,
      "node_type": "function",
      "name": "pause",
      "file": "autonomous-agent-contracts_contracts_testing_AutonomousAgentDeployerUpgradeTest.sol"
    },
    {
      "node_id": 38,
      "node_type": "function",
      "name": "unpause",
      "file": "autonomous-agent-contracts_contracts_testing_AutonomousAgentDeployerUpgradeTest.sol"
    },
    {
      "node_id": 39,
      "node_type": "function",
      "name": "isAgentToken",
      "file": "autonomous-agent-contracts_contracts_testing_AutonomousAgentDeployerUpgradeTest.sol"
    },
    {
      "node_id": 40,
      "node_type": "function",
      "name": "setPauser",
      "file": "autonomous-agent-contracts_contracts_testing_AutonomousAgentDeployerUpgradeTest.sol"
    },
    {
      "node_id": 41,
      "node_type": "function",
      "name": "setDistributor",
      "file": "autonomous-agent-contracts_contracts_testing_AutonomousAgentDeployerUpgradeTest.sol"
    },
    {
      "node_id": 42,
      "node_type": "function",
      "name": "setSpectralStaking",
      "file": "autonomous-agent-contracts_contracts_testing_AutonomousAgentDeployerUpgradeTest.sol"
    },
    {
      "node_id": 43,
      "node_type": "function",
      "name": "initialize",
      "file": "autonomous-agent-contracts_contracts_testing_MockSpectralStaking.sol"
    },
    {
      "node_id": 44,
      "node_type": "function",
      "name": "setAdmin",
      "file": "autonomous-agent-contracts_contracts_testing_MockSpectralStaking.sol"
    },
    {
      "node_id": 45,
      "node_type": "function",
      "name": "addDistribution",
      "file": "autonomous-agent-contracts_contracts_testing_MockSpectralStaking.sol"
    },
    {
      "node_id": 46,
      "node_type": "function",
      "name": "addDistributionToBuffer",
      "file": "autonomous-agent-contracts_contracts_testing_MockSpectralStaking.sol"
    },
    {
      "node_id": 47,
      "node_type": "function",
      "name": "releaseDistributionBuffer",
      "file": "autonomous-agent-contracts_contracts_testing_MockSpectralStaking.sol"
    },
    {
      "node_id": 48,
      "node_type": "function",
      "name": "_releaseDistributionBuffer",
      "file": "autonomous-agent-contracts_contracts_testing_MockSpectralStaking.sol"
    },
    {
      "node_id": 49,
      "node_type": "function",
      "name": "_addDistribution",
      "file": "autonomous-agent-contracts_contracts_testing_MockSpectralStaking.sol"
    },
    {
      "node_id": 50,
      "node_type": "function",
      "name": "_transferDistributionRewards",
      "file": "autonomous-agent-contracts_contracts_testing_MockSpectralStaking.sol"
    },
    {
      "node_id": 51,
      "node_type": "function",
      "name": "stake",
      "file": "autonomous-agent-contracts_contracts_testing_MockSpectralStaking.sol"
    },
    {
      "node_id": 52,
      "node_type": "function",
      "name": "withdraw",
      "file": "autonomous-agent-contracts_contracts_testing_MockSpectralStaking.sol"
    },
    {
      "node_id": 53,
      "node_type": "function",
      "name": "_claim",
      "file": "autonomous-agent-contracts_contracts_testing_MockSpectralStaking.sol"
    },
    {
      "node_id": 54,
      "node_type": "function",
      "name": "claim",
      "file": "autonomous-agent-contracts_contracts_testing_MockSpectralStaking.sol"
    },
    {
      "node_id": 55,
      "node_type": "function",
      "name": "claimBatch",
      "file": "autonomous-agent-contracts_contracts_testing_MockSpectralStaking.sol"
    },
    {
      "node_id": 56,
      "node_type": "function",
      "name": "transferCalibration",
      "file": "autonomous-agent-contracts_contracts_testing_MockSpectralStaking.sol"
    },
    {
      "node_id": 57,
      "node_type": "function",
      "name": "setBufferBundlingPeriod",
      "file": "autonomous-agent-contracts_contracts_testing_MockSpectralStaking.sol"
    },
    {
      "node_id": 58,
      "node_type": "function",
      "name": "_authorizeUpgrade",
      "file": "autonomous-agent-contracts_contracts_testing_MockSpectralStaking.sol"
    },
    {
      "node_id": 59,
      "node_type": "state_var",
      "name": "agentWallets",
      "file": "autonomous-agent-contracts_contracts_testing_AgentBalancesUpgradeTest.sol"
    },
    {
      "node_id": 60,
      "node_type": "state_var",
      "name": "agentBalance",
      "file": "autonomous-agent-contracts_contracts_testing_AgentBalancesUpgradeTest.sol"
    },
    {
      "node_id": 61,
      "node_type": "state_var",
      "name": "agentETHBalance",
      "file": "autonomous-agent-contracts_contracts_testing_AgentBalancesUpgradeTest.sol"
    },
    {
      "node_id": 62,
      "node_type": "state_var",
      "name": "admin",
      "file": "autonomous-agent-contracts_contracts_testing_AgentBalancesUpgradeTest.sol"
    },
    {
      "node_id": 63,
      "node_type": "state_var",
      "name": "version",
      "file": "autonomous-agent-contracts_contracts_testing_AgentBalancesUpgradeTest.sol"
    },
    {
      "node_id": 64,
      "node_type": "state_var",
      "name": "deployer",
      "file": "autonomous-agent-contracts_contracts_testing_AgentBalancesUpgradeTest.sol"
    },
    {
      "node_id": 65,
      "node_type": "state_var",
      "name": "__gap",
      "file": "autonomous-agent-contracts_contracts_testing_AgentBalancesUpgradeTest.sol"
    },
    {
      "node_id": 66,
      "node_type": "state_var",
      "name": "parameters",
      "file": "autonomous-agent-contracts_contracts_testing_AutonomousAgentDeployerUpgradeTest.sol"
    },
    {
      "node_id": 67,
      "node_type": "state_var",
      "name": "feeWallet",
      "file": "autonomous-agent-contracts_contracts_testing_AutonomousAgentDeployerUpgradeTest.sol"
    },
    {
      "node_id": 68,
      "node_type": "state_var",
      "name": "uniswapRouter",
      "file": "autonomous-agent-contracts_contracts_testing_AutonomousAgentDeployerUpgradeTest.sol"
    },
    {
      "node_id": 69,
      "node_type": "state_var",
      "name": "uniswapV3Router",
      "file": "autonomous-agent-contracts_contracts_testing_AutonomousAgentDeployerUpgradeTest.sol"
    },
    {
      "node_id": 70,
      "node_type": "state_var",
      "name": "uniswapFactory",
      "file": "autonomous-agent-contracts_contracts_testing_AutonomousAgentDeployerUpgradeTest.sol"
    },
    {
      "node_id": 71,
      "node_type": "state_var",
      "name": "agentTokenImplementation",
      "file": "autonomous-agent-contracts_contracts_testing_AutonomousAgentDeployerUpgradeTest.sol"
    },
    {
      "node_id": 72,
      "node_type": "state_var",
      "name": "UNISWAP_POOL_CREATION_VALUE",
      "file": "autonomous-agent-contracts_contracts_testing_AutonomousAgentDeployerUpgradeTest.sol"
    },
    {
      "node_id": 73,
      "node_type": "state_var",
      "name": "spectralToken",
      "file": "autonomous-agent-contracts_contracts_testing_AutonomousAgentDeployerUpgradeTest.sol"
    },
    {
      "node_id": 74,
      "node_type": "state_var",
      "name": "WETH",
      "file": "autonomous-agent-contracts_contracts_testing_AutonomousAgentDeployerUpgradeTest.sol"
    },
    {
      "node_id": 75,
      "node_type": "state_var",
      "name": "agentBalances",
      "file": "autonomous-agent-contracts_contracts_testing_AutonomousAgentDeployerUpgradeTest.sol"
    },
    {
      "node_id": 76,
      "node_type": "state_var",
      "name": "agentTokens",
      "file": "autonomous-agent-contracts_contracts_testing_AutonomousAgentDeployerUpgradeTest.sol"
    },
    {
      "node_id": 77,
      "node_type": "state_var",
      "name": "agentTokensSold",
      "file": "autonomous-agent-contracts_contracts_testing_AutonomousAgentDeployerUpgradeTest.sol"
    },
    {
      "node_id": 78,
      "node_type": "state_var",
      "name": "agentWallets",
      "file": "autonomous-agent-contracts_contracts_testing_AutonomousAgentDeployerUpgradeTest.sol"
    },
    {
      "node_id": 79,
      "node_type": "state_var",
      "name": "totalSPECDeposited",
      "file": "autonomous-agent-contracts_contracts_testing_AutonomousAgentDeployerUpgradeTest.sol"
    },
    {
      "node_id": 80,
      "node_type": "state_var",
      "name": "agentTokenUniswapPool",
      "file": "autonomous-agent-contracts_contracts_testing_AutonomousAgentDeployerUpgradeTest.sol"
    },
    {
      "node_id": 81,
      "node_type": "state_var",
      "name": "admin",
      "file": "autonomous-agent-contracts_contracts_testing_AutonomousAgentDeployerUpgradeTest.sol"
    },
    {
      "node_id": 82,
      "node_type": "state_var",
      "name": "version",
      "file": "autonomous-agent-contracts_contracts_testing_AutonomousAgentDeployerUpgradeTest.sol"
    },
    {
      "node_id": 83,
      "node_type": "state_var",
      "name": "agentsVersion",
      "file": "autonomous-agent-contracts_contracts_testing_AutonomousAgentDeployerUpgradeTest.sol"
    },
    {
      "node_id": 84,
      "node_type": "state_var",
      "name": "paused",
      "file": "autonomous-agent-contracts_contracts_testing_AutonomousAgentDeployerUpgradeTest.sol"
    },
    {
      "node_id": 85,
      "node_type": "state_var",
      "name": "pauser",
      "file": "autonomous-agent-contracts_contracts_testing_AutonomousAgentDeployerUpgradeTest.sol"
    },
    {
      "node_id": 86,
      "node_type": "state_var",
      "name": "INITIAL_VIRTUAL_LIQUIDITY",
      "file": "autonomous-agent-contracts_contracts_testing_AutonomousAgentDeployerUpgradeTest.sol"
    },
    {
      "node_id": 87,
      "node_type": "state_var",
      "name": "distributor",
      "file": "autonomous-agent-contracts_contracts_testing_AutonomousAgentDeployerUpgradeTest.sol"
    },
    {
      "node_id": 88,
      "node_type": "state_var",
      "name": "spectralStaking",
      "file": "autonomous-agent-contracts_contracts_testing_AutonomousAgentDeployerUpgradeTest.sol"
    },
    {
      "node_id": 89,
      "node_type": "state_var",
      "name": "accumulatedTaxToSwap",
      "file": "autonomous-agent-contracts_contracts_testing_AutonomousAgentDeployerUpgradeTest.sol"
    },
    {
      "node_id": 90,
      "node_type": "state_var",
      "name": "accumulatedTaxToSwapByAgent",
      "file": "autonomous-agent-contracts_contracts_testing_AutonomousAgentDeployerUpgradeTest.sol"
    },
    {
      "node_id": 91,
      "node_type": "state_var",
      "name": "__gap",
      "file": "autonomous-agent-contracts_contracts_testing_AutonomousAgentDeployerUpgradeTest.sol"
    },
    {
      "node_id": 92,
      "node_type": "state_var",
      "name": "spectralToken",
      "file": "autonomous-agent-contracts_contracts_testing_MockSpectralStaking.sol"
    },
    {
      "node_id": 93,
      "node_type": "state_var",
      "name": "stakingToken",
      "file": "autonomous-agent-contracts_contracts_testing_MockSpectralStaking.sol"
    },
    {
      "node_id": 94,
      "node_type": "state_var",
      "name": "admin",
      "file": "autonomous-agent-contracts_contracts_testing_MockSpectralStaking.sol"
    },
    {
      "node_id": 95,
      "node_type": "state_var",
      "name": "version",
      "file": "autonomous-agent-contracts_contracts_testing_MockSpectralStaking.sol"
    },
    {
      "node_id": 96,
      "node_type": "state_var",
      "name": "totalStaked",
      "file": "autonomous-agent-contracts_contracts_testing_MockSpectralStaking.sol"
    },
    {
      "node_id": 97,
      "node_type": "state_var",
      "name": "totalDebtWeight",
      "file": "autonomous-agent-contracts_contracts_testing_MockSpectralStaking.sol"
    },
    {
      "node_id": 98,
      "node_type": "state_var",
      "name": "distributionCount",
      "file": "autonomous-agent-contracts_contracts_testing_MockSpectralStaking.sol"
    },
    {
      "node_id": 99,
      "node_type": "state_var",
      "name": "distributionBufferBundlingPeriod",
      "file": "autonomous-agent-contracts_contracts_testing_MockSpectralStaking.sol"
    },
    {
      "node_id": 100,
      "node_type": "state_var",
      "name": "PRECISION",
      "file": "autonomous-agent-contracts_contracts_testing_MockSpectralStaking.sol"
    },
    {
      "node_id": 101,
      "node_type": "state_var",
      "name": "CLAIM_WITHDRAW_DELAY",
      "file": "autonomous-agent-contracts_contracts_testing_MockSpectralStaking.sol"
    },
    {
      "node_id": 102,
      "node_type": "state_var",
      "name": "lastDeposit",
      "file": "autonomous-agent-contracts_contracts_testing_MockSpectralStaking.sol"
    },
    {
      "node_id": 103,
      "node_type": "state_var",
      "name": "lastClaimedIndex",
      "file": "autonomous-agent-contracts_contracts_testing_MockSpectralStaking.sol"
    },
    {
      "node_id": 104,
      "node_type": "state_var",
      "name": "distributions",
      "file": "autonomous-agent-contracts_contracts_testing_MockSpectralStaking.sol"
    },
    {
      "node_id": 105,
      "node_type": "state_var",
      "name": "userDistributions",
      "file": "autonomous-agent-contracts_contracts_testing_MockSpectralStaking.sol"
    },
    {
      "node_id": 106,
      "node_type": "state_var",
      "name": "distributionBuffer",
      "file": "autonomous-agent-contracts_contracts_testing_MockSpectralStaking.sol"
    },
    {
      "node_id": 107,
      "node_type": "state_var",
      "name": "deployer",
      "file": "autonomous-agent-contracts_contracts_testing_MockSpectralStaking.sol"
    },
    {
      "node_id": 108,
      "node_type": "state_var",
      "name": "__gap",
      "file": "autonomous-agent-contracts_contracts_testing_MockSpectralStaking.sol"
    },
    {
      "node_id": 109,
      "node_type": "call_site",
      "name": "TRANSFER:autonomous-agent-contracts_contracts_testing_AgentBalancesUpgradeTest.sol:92",
      "file": "autonomous-agent-contracts_contracts_testing_AgentBalancesUpgradeTest.sol"
    },
    {
      "node_id": 110,
      "node_type": "call_site",
      "name": "TRANSFER:autonomous-agent-contracts_contracts_testing_AgentBalancesUpgradeTest.sol:115",
      "file": "autonomous-agent-contracts_contracts_testing_AgentBalancesUpgradeTest.sol"
    },
    {
      "node_id": 111,
      "node_type": "call_site",
      "name": "TRANSFER:autonomous-agent-contracts_contracts_testing_AgentBalancesUpgradeTest.sol:136",
      "file": "autonomous-agent-contracts_contracts_testing_AgentBalancesUpgradeTest.sol"
    },
    {
      "node_id": 112,
      "node_type": "call_site",
      "name": "TRANSFER:autonomous-agent-contracts_contracts_testing_AutonomousAgentDeployerUpgradeTest.sol:169",
      "file": "autonomous-agent-contracts_contracts_testing_AutonomousAgentDeployerUpgradeTest.sol"
    },
    {
      "node_id": 113,
      "node_type": "call_site",
      "name": "TRANSFER:autonomous-agent-contracts_contracts_testing_AutonomousAgentDeployerUpgradeTest.sol:203",
      "file": "autonomous-agent-contracts_contracts_testing_AutonomousAgentDeployerUpgradeTest.sol"
    },
    {
      "node_id": 114,
      "node_type": "call_site",
      "name": "INTERFACE_CALL:autonomous-agent-contracts_contracts_testing_AutonomousAgentDeployerUpgradeTest.sol:226",
      "file": "autonomous-agent-contracts_contracts_testing_AutonomousAgentDeployerUpgradeTest.sol"
    },
    {
      "node_id": 115,
      "node_type": "call_site",
      "name": "TRANSFER:autonomous-agent-contracts_contracts_testing_AutonomousAgentDeployerUpgradeTest.sol:228",
      "file": "autonomous-agent-contracts_contracts_testing_AutonomousAgentDeployerUpgradeTest.sol"
    },
    {
      "node_id": 116,
      "node_type": "call_site",
      "name": "INTERFACE_CALL:autonomous-agent-contracts_contracts_testing_AutonomousAgentDeployerUpgradeTest.sol:231",
      "file": "autonomous-agent-contracts_contracts_testing_AutonomousAgentDeployerUpgradeTest.sol"
    },
    {
      "node_id": 117,
      "node_type": "call_site",
      "name": "INTERFACE_CALL:autonomous-agent-contracts_contracts_testing_AutonomousAgentDeployerUpgradeTest.sol:234",
      "file": "autonomous-agent-contracts_contracts_testing_AutonomousAgentDeployerUpgradeTest.sol"
    },
    {
      "node_id": 118,
      "node_type": "call_site",
      "name": "CALL:autonomous-agent-contracts_contracts_testing_AutonomousAgentDeployerUpgradeTest.sol:239",
      "file": "autonomous-agent-contracts_contracts_testing_AutonomousAgentDeployerUpgradeTest.sol"
    },
    {
      "node_id": 119,
      "node_type": "call_site",
      "name": "INTERFACE_CALL:autonomous-agent-contracts_contracts_testing_AutonomousAgentDeployerUpgradeTest.sol:243",
      "file": "autonomous-agent-contracts_contracts_testing_AutonomousAgentDeployerUpgradeTest.sol"
    },
    {
      "node_id": 120,
      "node_type": "call_site",
      "name": "INTERFACE_CALL:autonomous-agent-contracts_contracts_testing_AutonomousAgentDeployerUpgradeTest.sol:273",
      "file": "autonomous-agent-contracts_contracts_testing_AutonomousAgentDeployerUpgradeTest.sol"
    },
    {
      "node_id": 121,
      "node_type": "call_site",
      "name": "INTERFACE_CALL:autonomous-agent-contracts_contracts_testing_AutonomousAgentDeployerUpgradeTest.sol:302",
      "file": "autonomous-agent-contracts_contracts_testing_AutonomousAgentDeployerUpgradeTest.sol"
    },
    {
      "node_id": 122,
      "node_type": "call_site",
      "name": "INTERFACE_CALL:autonomous-agent-contracts_contracts_testing_AutonomousAgentDeployerUpgradeTest.sol:348",
      "file": "autonomous-agent-contracts_contracts_testing_AutonomousAgentDeployerUpgradeTest.sol"
    },
    {
      "node_id": 123,
      "node_type": "call_site",
      "name": "INTERFACE_CALL:autonomous-agent-contracts_contracts_testing_AutonomousAgentDeployerUpgradeTest.sol:366",
      "file": "autonomous-agent-contracts_contracts_testing_AutonomousAgentDeployerUpgradeTest.sol"
    },
    {
      "node_id": 124,
      "node_type": "call_site",
      "name": "INTERFACE_CALL:autonomous-agent-contracts_contracts_testing_AutonomousAgentDeployerUpgradeTest.sol:396",
      "file": "autonomous-agent-contracts_contracts_testing_AutonomousAgentDeployerUpgradeTest.sol"
    },
    {
      "node_id": 125,
      "node_type": "call_site",
      "name": "INTERFACE_CALL:autonomous-agent-contracts_contracts_testing_AutonomousAgentDeployerUpgradeTest.sol:402",
      "file": "autonomous-agent-contracts_contracts_testing_AutonomousAgentDeployerUpgradeTest.sol"
    },
    {
      "node_id": 126,
      "node_type": "call_site",
      "name": "TRANSFER:autonomous-agent-contracts_contracts_testing_AutonomousAgentDeployerUpgradeTest.sol:430",
      "file": "autonomous-agent-contracts_contracts_testing_AutonomousAgentDeployerUpgradeTest.sol"
    },
    {
      "node_id": 127,
      "node_type": "call_site",
      "name": "INTERFACE_CALL:autonomous-agent-contracts_contracts_testing_AutonomousAgentDeployerUpgradeTest.sol:432",
      "file": "autonomous-agent-contracts_contracts_testing_AutonomousAgentDeployerUpgradeTest.sol"
    },
    {
      "node_id": 128,
      "node_type": "call_site",
      "name": "CALL:autonomous-agent-contracts_contracts_testing_AutonomousAgentDeployerUpgradeTest.sol:455",
      "file": "autonomous-agent-contracts_contracts_testing_AutonomousAgentDeployerUpgradeTest.sol"
    },
    {
      "node_id": 129,
      "node_type": "call_site",
      "name": "INTERFACE_CALL:autonomous-agent-contracts_contracts_testing_MockSpectralStaking.sol:298",
      "file": "autonomous-agent-contracts_contracts_testing_MockSpectralStaking.sol"
    },
    {
      "node_id": 130,
      "node_type": "call_site",
      "name": "INTERFACE_CALL:autonomous-agent-contracts_contracts_testing_MockSpectralStaking.sol:317",
      "file": "autonomous-agent-contracts_contracts_testing_MockSpectralStaking.sol"
    },
    {
      "node_id": 131,
      "node_type": "call_site",
      "name": "INTERFACE_CALL:autonomous-agent-contracts_contracts_testing_MockSpectralStaking.sol:338",
      "file": "autonomous-agent-contracts_contracts_testing_MockSpectralStaking.sol"
    },
    {
      "node_id": 132,
      "node_type": "call_site",
      "name": "INTERFACE_CALL:autonomous-agent-contracts_contracts_testing_MockSpectralStaking.sol:359",
      "file": "autonomous-agent-contracts_contracts_testing_MockSpectralStaking.sol"
    },
    {
      "node_id": 133,
      "node_type": "call_site",
      "name": "INTERFACE_CALL:autonomous-agent-contracts_contracts_testing_MockSpectralStaking.sol:361",
      "file": "autonomous-agent-contracts_contracts_testing_MockSpectralStaking.sol"
    },
    {
      "node_id": 134,
      "node_type": "call_site",
      "name": "TRANSFER:autonomous-agent-contracts_contracts_testing_MockSpectralStaking.sol:434",
      "file": "autonomous-agent-contracts_contracts_testing_MockSpectralStaking.sol"
    },
    {
      "node_id": 135,
      "node_type": "call_site",
      "name": "TRANSFER:autonomous-agent-contracts_contracts_testing_MockSpectralStaking.sol:441",
      "file": "autonomous-agent-contracts_contracts_testing_MockSpectralStaking.sol"
    },
    {
      "node_id": 136,
      "node_type": "call_site",
      "name": "INTERFACE_CALL:autonomous-agent-contracts_contracts_testing_MockSpectralStaking.sol:468",
      "file": "autonomous-agent-contracts_contracts_testing_MockSpectralStaking.sol"
    }
  ],
  "stats": {
    "n_nodes": 137,
    "n_hyperedges": 28,
    "n_functions": 59,
    "n_state_vars": 50,
    "n_call_sites": 28,
    "avg_hyperedge_size": 10.607142857142858
  },
  "label": {
    "vfp_id": "neg_00514",
    "label_vector": {
      "reentrancy": 0,
      "arithmetic_oracle": 0,
      "defi_protection": 0,
      "access_control": 0,
      "state_management": 0,
      "unchecked_call": 0,
      "input_validation": 0
    },
    "source": "forge_negative"
  }
}